autotds/__init__.py
autotds-0.0.4.dist-info/LICENSE
autotds-0.0.4.dist-info/METADATA
autotds-0.0.4.dist-info/WHEEL
autotds-0.0.4.dist-info/entry_points.txt
autotds-0.0.4.dist-info/top_level.txt
autotds-0.0.4.dist-info/RECORD
