Metadata-Version: 2.1
Name: autotds
Version: 0.0.4
Summary: Generate Towards Data Science (TDS) quality articles
Home-page: https://github.com/microprediction/autotds
Author: microprediction
Author-email: pcotton@intechinvestments.com
License: MIT
Platform: UNKNOWN
Classifier: License :: OSI Approved :: MIT License
Classifier: Programming Language :: Python :: 3
Classifier: Programming Language :: Python :: 3.7
Requires-Dist: wheel
Requires-Dist: pathlib
Requires-Dist: numpy (>=1.19.5)
Requires-Dist: importlib-metadata (>=1.7.0)
Requires-Dist: getjson
